Metadata-Version: 2.4
Name: llm-tools-anki
Version: 0.1.1
Summary: Manage Anki cards with the LLM tool
Author: Alex Ledger
License-Expression: Apache-2.0
Project-URL: Homepage, https://github.com/aled102/llm-tools-anki
Project-URL: Changelog, https://github.com/aled102/llm-tools-anki/releases
Project-URL: Issues, https://github.com/aled102/llm-tools-anki/issues
Project-URL: CI, https://github.com/aled102/llm-tools-anki/actions
Requires-Python: >=3.9
License-File: LICENSE
Requires-Dist: httpx>=0.28.1
Requires-Dist: llm
Provides-Extra: test
Requires-Dist: pytest; extra == "test"
Requires-Dist: llm-echo>=0.3a1; extra == "test"
Dynamic: license-file
